sluurp/__init__.py
sluurp/executor.py
sluurp/job.py
sluurp/utils.py
sluurp/tests/test_executor.py
sluurp/tests/test_job.py
sluurp/tests/test_utils.py
sluurp-0.4.6.dist-info/licenses/LICENSE.md
sluurp-0.4.6.dist-info/METADATA
sluurp-0.4.6.dist-info/WHEEL
sluurp-0.4.6.dist-info/top_level.txt
sluurp-0.4.6.dist-info/RECORD
